{
	"groups":[
	{
		"keys":"",
		"name":"loading"
	},
	{
		"keys":"chuzhan,startbg,startbtn,bg,Chopper1_2,Chopper1_1,hp,Bomb,pause,bombbtn,go,home,Enemy6,Enemy1,Enemy2,Enemy3,Enemy4,Enemy5,xb_bullet1,xb_bullet2,baozha0,baozha1,baozha2,baozha3,baozha4,p_bullet_2,p_bullet_1,promp_boom,promp_bullet,promp_hp,promp_score,boss_bullet,pauseTip,o_bg,o_down,o_fuzhi,o_more,o_rstart,o_share,bgsound,music_close,music_open,logo",
		"name":"runNeed"
	}],
	"resources":[
	{
		"name":"chuzhan",
		"type":"image",
		"url":"assets/chuzhan.png"
	},
	{
		"name":"startbg",
		"type":"image",
		"url":"assets/startbg.jpg"
	},
	{
		"name":"startbtn",
		"type":"image",
		"url":"assets/startbtn.png"
	},
	{
		"name":"bg",
		"type":"image",
		"url":"assets/bg.png"
	},
	{
		"name":"Chopper1_2",
		"type":"image",
		"url":"assets/Chopper1_2.png"
	},
	{
		"name":"Chopper1_1",
		"type":"image",
		"url":"assets/Chopper1_1.png"
	},
	{
		"name":"hp",
		"type":"image",
		"url":"assets/hp.png"
	},
	{
		"name":"Bomb",
		"type":"image",
		"url":"assets/Bomb.png"
	},
	{
		"name":"pause",
		"type":"image",
		"url":"assets/pause.png"
	},
	{
		"name":"bombbtn",
		"type":"image",
		"url":"assets/bombbtn.png"
	},
	{
		"name":"go",
		"type":"image",
		"url":"assets/go.png"
	},
	{
		"name":"home",
		"type":"image",
		"url":"assets/home.png"
	},
	{
		"name":"Enemy6",
		"type":"image",
		"url":"assets/Enemy6.png"
	},
	{
		"name":"Enemy1",
		"type":"image",
		"url":"assets/Enemy1.png"
	},
	{
		"name":"Enemy2",
		"type":"image",
		"url":"assets/Enemy2.png"
	},
	{
		"name":"Enemy3",
		"type":"image",
		"url":"assets/Enemy3.png"
	},
	{
		"name":"Enemy4",
		"type":"image",
		"url":"assets/Enemy4.png"
	},
	{
		"name":"Enemy5",
		"type":"image",
		"url":"assets/Enemy5.png"
	},
	{
		"name":"xb_bullet1",
		"type":"image",
		"url":"assets/xb_bullet1.png"
	},
	{
		"name":"xb_bullet2",
		"type":"image",
		"url":"assets/xb_bullet2.png"
	},
	{
		"name":"baozha0",
		"type":"image",
		"url":"assets/baozha0001.png"
	},
	{
		"name":"baozha1",
		"type":"image",
		"url":"assets/baozha0003.png"
	},
	{
		"name":"baozha2",
		"type":"image",
		"url":"assets/baozha0004.png"
	},
	{
		"name":"baozha3",
		"type":"image",
		"url":"assets/baozha0008.png"
	},
	{
		"name":"baozha4",
		"type":"image",
		"url":"assets/baozha0011.png"
	},
	{
		"name":"p_bullet_2",
		"type":"image",
		"url":"assets/p_bullet_2.png"
	},
	{
		"name":"p_bullet_1",
		"type":"image",
		"url":"assets/p_bullet_1.png"
	},
	{
		"name":"promp_boom",
		"type":"image",
		"url":"assets/promp_boom.png"
	},
	{
		"name":"promp_bullet",
		"type":"image",
		"url":"assets/promp_bullet.png"
	},
	{
		"name":"promp_hp",
		"type":"image",
		"url":"assets/promp_hp.png"
	},
	{
		"name":"promp_score",
		"type":"image",
		"url":"assets/promp_score.png"
	},
	{
		"name":"boss_bullet",
		"type":"image",
		"url":"assets/boss_bullet.png"
	},
	{
		"name":"pauseTip",
		"type":"image",
		"url":"assets/pauseTip.png"
	},
	{
		"name":"o_bg",
		"type":"image",
		"url":"assets/o_bg.png"
	},
	{
		"name":"o_down",
		"type":"image",
		"url":"assets/o_down.png"
	},
	{
		"name":"o_fuzhi",
		"type":"image",
		"url":"assets/o_fuzhi.png"
	},
	{
		"name":"o_more",
		"type":"image",
		"url":"assets/o_more.png"
	},
	{
		"name":"o_rstart",
		"type":"image",
		"url":"assets/o_rstart.png"
	},
	{
		"name":"o_share",
		"type":"image",
		"url":"assets/o_share.png"
	},
	{
		"name":"bgsound",
		"soundType":"music",
		"type":"sound",
		"url":"assets/bgsound.mp3"
	},
	{
		"name":"music_close",
		"type":"image",
		"url":"assets/music_close.png"
	},
	{
		"name":"music_open",
		"type":"image",
		"url":"assets/music_open.png"
	},
	{
		"name":"logo",
		"type":"image",
		"url":"assets/logo.png"
	}]
}